AUTHORS.rst
CHANGELOG.rst
CONTRIBUTING.rst
LICENSE
MANIFEST.in
README.rst
setup.cfg
setup.py
devenv/__init__.py
devenv/cli.py
devenv/config.py
devenv/devenv.py
devenv.egg-info/PKG-INFO
devenv.egg-info/SOURCES.txt
devenv.egg-info/dependency_links.txt
devenv.egg-info/entry_points.txt
devenv.egg-info/not-zip-safe
devenv.egg-info/requires.txt
devenv.egg-info/top_level.txt
docs/Makefile
docs/authors.rst
docs/conf.py
docs/contributing.rst
docs/history.rst
docs/index.rst
docs/installation.rst
docs/make.bat
docs/readme.rst
docs/usage.rst
tests/__init__.py
tests/test_devenv.py