Metadata-Version: 1.1
Name: devenv
Version: 0.1.1
Summary: A development environment based upon docker.
Home-page: https://github.com/FlorianLudwig/devenv
Author: Florian Ludwig
Author-email: f.ludwig@greyrook.com
License: Apache Software License 2.0
Keywords: devenv
Platform: UNKNOWN
Classifier: Development Status :: 2 - Pre-Alpha
Classifier: Intended Audience :: Developers
Classifier: License :: OSI Approved :: Apache Software License
Classifier: Natural Language :: English
Classifier: Programming Language :: Python :: 2
Classifier: Programming Language :: Python :: 2.6
Classifier: Programming Language :: Python :: 2.7
Classifier: Programming Language :: Python :: 3
Classifier: Programming Language :: Python :: 3.3
Classifier: Programming Language :: Python :: 3.4
Classifier: Programming Language :: Python :: 3.5
